llama_index/indices/managed/zilliz/__init__.py
llama_index/indices/managed/zilliz/base.py
llama_index/indices/managed/zilliz/retriever.py
llama_index_indices_managed_zilliz-0.2.0.dist-info/METADATA
llama_index_indices_managed_zilliz-0.2.0.dist-info/WHEEL
llama_index_indices_managed_zilliz-0.2.0.dist-info/RECORD
